{"weight":0.015667974948883058,"featureIndex":98,"threshold":-0.7284331321716309,"left":{"weight":0.08672827482223511,"featureIndex":182,"threshold":-1.37510085105896,"left":{"aggregate":[1.0,16.0]},"right":{"weight":0.17416006326675416,"featureIndex":319,"partition":[true,true,true,true,false,true,true,true,false,false,false,true,false,false,false,false,true,false,false,false,false,true,true,false,true,false,true,true,true,false,true,false,false,true,true,true,false,true,false,false,false,false,false,false,false,false,true,true,false,false,false],"left":{"weight":0.14686447381973267,"featureIndex":45,"threshold":1.0756771564483643,"left":{"aggregate":[23.0,30.0]},"right":{"aggregate":[0.0,14.0]}},"right":{"weight":0.2459816038608551,"featureIndex":326,"partition":[false,true,true,true,false,false,true,false,false,false,true,true,false,false,false,false,false,true,false,true,false,true,true,true,false,true,false,false,false,false,false,false,false,false,false,false,false,false,false,false,false,false,false,false,false,false,false,false,false,false,true,false,false,false,false,false,false,true,false,false,false,false,true,false,true,false,true,false,false,false,true,false,false,true,true,false,false,true],"left":{"aggregate":[94.0,0.0]},"right":{"aggregate":[36.0,24.0]}}}},"right":{"weight":0.013052225112915039,"featureIndex":135,"threshold":0.3162832260131836,"left":{"weight":0.029299557209014894,"featureIndex":19,"threshold":1.3240208625793458,"left":{"weight":0.022478699684143068,"featureIndex":61,"threshold":2.010063409805298,"left":{"weight":0.02424722909927368,"featureIndex":16,"threshold":-0.20511865615844727,"left":{"weight":0.05121159553527832,"featureIndex":288,"threshold":-1.6554200649261475,"left":{"aggregate":[11.0,0.0]},"right":{"weight":0.054727017879486087,"featureIndex":1,"threshold":-1.4089303016662598,"left":{"aggregate":[2.0,19.0]},"right":{"weight":0.04666513204574585,"featureIndex":287,"threshold":-0.4680666923522949,"left":{"weight":0.18971580266952516,"featureIndex":174,"threshold":-1.0329701900482178,"left":{"aggregate":[8.0,0.0]},"right":{"aggregate":[17.0,45.0]}},"right":{"weight":0.2059180736541748,"featureIndex":298,"partition":[true,false,false,false,false,true,false,true,false,false,false,false,false,true,true,true,false,false,false,false,false,false,true,true,false,false,false,false,false,false,true,true,false,false,true,false,true,false,false,false,true,false,false,true,false,false,false,false,true],"left":{"weight":0.08227235078811646,"featureIndex":216,"threshold":-1.705255150794983,"left":{"aggregate":[0.0,7.0]},"right":{"weight":0.15001428127288819,"featureIndex":0,"partition":[false,true,true,false,false,true,false,false,true,false,false,false,false,false,false,false,false,false,true],"left":{"aggregate":[14.0,30.0]},"right":{"aggregate":[21.0,6.0]}}},"right":{"aggregate":[38.0,2.0]}}}}},"right":{"weight":0.04057002067565918,"featureIndex":198,"threshold":-1.2210109233856202,"left":{"aggregate":[3.0,43.0]},"right":{"weight":0.0748324990272522,"featureIndex":18,"threshold":0.10117697715759278,"left":{"weight":0.100300133228302,"featureIndex":323,"partition":[false,true,true,true,true,false,true,true,false,false,false,false,false,false,false,true,false,false,true,true,false,false,true,true,true,false,false,false],"left":{"weight":0.1201545000076294,"featureIndex":275,"threshold":-0.4365575313568115,"left":{"aggregate":[1.0,21.0]},"right":{"aggregate":[20.0,29.0]}},"right":{"weight":0.12694895267486573,"featureIndex":304,"partition":[false,true,false,true,false,true,true,false,false,true,false,false,false,false,false,false,false,false,false,true,true,true,false,false,true,true,false,false,false,false,false,true,false,false],"left":{"aggregate":[22.0,24.0]},"right":{"aggregate":[38.0,6.0]}}},"right":{"weight":0.19275504350662232,"featureIndex":319,"partition":[true,false,true,false,false,false,false,false,false,false,true,true,false,true,false,true,false,false,false,false,true,false,false,false,false,true,false,false,true,false,false,false,false,true,false,false,true,false,true,true,false,true,true,true,false,false,false,false,false,false,false],"left":{"weight":0.16350853443145753,"featureIndex":338,"partition":[true,false,false,true,false,false,true,false,true,false,false,true,false,false,false,false],"left":{"weight":0.16982388496398927,"featureIndex":304,"partition":[false,true,false,true,true,true,false,false,false,false,false,false,false,false,false,false,false,true,false,true,true,false,false,true,true,true,false,false,false,false,false,false,false,false],"left":{"aggregate":[10.0,5.0]},"right":{"aggregate":[7.0,46.0]}},"right":{"aggregate":[12.0,2.0]}},"right":{"aggregate":[0.0,64.0]}}}}},"right":{"aggregate":[0.0,19.0]}},"right":{"aggregate":[41.0,15.0]}},"right":{"weight":0.04221898317337036,"featureIndex":48,"threshold":1.419240951538086,"left":{"weight":0.04170721769332886,"featureIndex":209,"threshold":1.3855855464935303,"left":{"weight":0.20337152481079102,"featureIndex":326,"partition":[true,true,true,false,false,false,false,true,false,true,true,true,true,true,true,true,true,false,false,true,false,true,false,false,false,false,false,false,false,false,true,false,true,true,false,false,false,true,false,false,false,false,true,false,false,false,false,true,false,true,false,false,true,true,true,false,false,false,true,false,false,true,false,false,false,false,false,true,false,false,true,true,false,false,false,false,true,false],"left":{"weight":0.054257214069366458,"featureIndex":218,"threshold":-1.2013757228851319,"left":{"aggregate":[12.0,4.0]},"right":{"weight":0.07380044460296631,"featureIndex":326,"partition":[false,false,false,false,false,false,true,false,true,false,false,false,false,false,false,false,false,true,false,false,false,false,false,true,false,false,true,true,true,false,false,false,false,false,false,false,false,false,false,false,false,false,false,true,true,false,false,false,false,false,false,false,false,false,false,false,false,false,false,false,false,false,true,true,false,true,false,false,false,false,false,false,false,true,false,false,false,false],"left":{"weight":0.09493917226791382,"featureIndex":280,"threshold":0.7977571487426758,"left":{"weight":0.13441306352615357,"featureIndex":185,"threshold":1.1164238452911378,"left":{"weight":0.13076680898666383,"featureIndex":338,"partition":[true,true,true,true,false,true,true,true,false,false,true,false,false,false,false,false],"left":{"aggregate":[14.0,1.0]},"right":{"aggregate":[27.0,34.0]}},"right":{"aggregate":[1.0,18.0]}},"right":{"aggregate":[2.0,27.0]}},"right":{"aggregate":[3.0,44.0]}}},"right":{"weight":0.10327756404876709,"featureIndex":177,"threshold":-0.40686917304992678,"left":{"aggregate":[53.0,1.0]},"right":{"weight":0.13071531057357789,"featureIndex":21,"threshold":0.5444808006286621,"left":{"aggregate":[34.0,19.0]},"right":{"aggregate":[17.0,0.0]}}}},"right":{"aggregate":[0.0,13.0]}},"right":{"aggregate":[42.0,8.0]}}}}