{"weight":0.06198781728744507,"featureIndex":326,"partition":[true,true,false,false,false,false,false,true,false,true,true,true,true,false,false,true,false,true,false,true,true,false,false,true,false,false,false,false,false,false,false,false,false,true,false,false,true,false,true,true,false,true,true,false,true,false,false,true,false,true,false,false,false,true,false,true,true,true,false,false,false,false,true,false,false,true,false,true,false,false,false,true,false,true,false,true,false,true,false],"left":{"weight":0.018022775650024415,"featureIndex":136,"threshold":-1.855015516281128,"left":{"aggregate":[1.0,26.0]},"right":{"weight":0.03851914405822754,"featureIndex":0,"partition":[true,true,true,true,true,true,true,true,true,false,true,true,false,false,true,false,true,false,false,false],"left":{"aggregate":[2.0,50.0]},"right":{"weight":0.0189211368560791,"featureIndex":120,"threshold":0.23020100593566895,"left":{"weight":0.11755025386810303,"featureIndex":327,"partition":[false,false,false,true,false,true,false,false,false,false,false,false,false,false,false,false,true,false,true,false,false,false,false,false,false,false,true,false,false,false,false,false,false,false,false,true,false,true,false,false,true,true,false,false,false,false,true,true,false,false,false,false,true,true,true,true,true,true,false,false,false],"left":{"weight":0.12761777639389039,"featureIndex":323,"partition":[true,false,false,false,true,true,false,false,true,true,false,false,true,false,false,true,false,false,true,false,true,false,false,false,false,true,false,false],"left":{"weight":0.13690930604934693,"featureIndex":322,"partition":[true,false,true,true,true,false,false,true,true,false,false,false,false,false,true,true,false,true,true,true,false,false,false,true,false,false,false],"left":{"aggregate":[1.0,20.0]},"right":{"weight":0.09640675783157349,"featureIndex":105,"threshold":1.162811040878296,"left":{"weight":0.10746216773986817,"featureIndex":97,"threshold":0.739675760269165,"left":{"weight":0.16216611862182618,"featureIndex":195,"threshold":1.0082340240478516,"left":{"aggregate":[39.0,23.0]},"right":{"aggregate":[0.0,9.0]}},"right":{"aggregate":[0.0,8.0]}},"right":{"aggregate":[9.0,0.0]}}},"right":{"weight":0.04199668765068054,"featureIndex":25,"threshold":-1.840329885482788,"left":{"aggregate":[2.0,0.0]},"right":{"weight":0.0613102912902832,"featureIndex":289,"threshold":0.3157668113708496,"left":{"weight":0.11821848154067993,"featureIndex":110,"threshold":0.3223550319671631,"left":{"aggregate":[4.0,54.0]},"right":{"aggregate":[8.0,10.0]}},"right":{"weight":0.03873483091592789,"featureIndex":24,"threshold":-1.6342284679412842,"left":{"aggregate":[1.0,7.0]},"right":{"aggregate":[0.0,86.0]}}}}},"right":{"weight":0.06904393434524536,"featureIndex":36,"threshold":1.3713188171386719,"left":{"weight":0.12671172618865968,"featureIndex":233,"threshold":0.4842867851257324,"left":{"weight":0.2055642306804657,"featureIndex":323,"partition":[false,false,false,false,false,false,false,false,false,true,false,false,false,true,false,true,false,false,false,false,false,false,true,false,false,false,false,false],"left":{"aggregate":[56.0,3.0]},"right":{"aggregate":[5.0,8.0]}},"right":{"aggregate":[26.0,31.0]}},"right":{"aggregate":[0.0,6.0]}}},"right":{"weight":0.09422504901885987,"featureIndex":336,"threshold":0.6017472743988037,"left":{"weight":0.0857425332069397,"featureIndex":123,"threshold":0.5259678363800049,"left":{"weight":0.14107966423034669,"featureIndex":300,"partition":[true,false,false,true,false,true,false,false,true,false,true,false,true,false,false,false,false,true,false,false,false,true,false,true,false,false,false,true,false,false,false,false,true,true,false,false,false,false,false,false,false,false,false,false,false,false,false,false,false,true,false,false,false,false,false,true,false,true,false,false,false,false,false,true,true,false,false,false],"left":{"weight":0.19494032859802247,"featureIndex":58,"threshold":0.7012815475463867,"left":{"aggregate":[32.0,26.0]},"right":{"aggregate":[23.0,0.0]}},"right":{"aggregate":[38.0,0.0]}},"right":{"aggregate":[26.0,34.0]}},"right":{"weight":0.10231691598892212,"featureIndex":288,"threshold":-1.3399492502212525,"left":{"aggregate":[8.0,1.0]},"right":{"weight":0.17470711469650269,"featureIndex":78,"threshold":0.06341338157653809,"left":{"weight":0.09316328167915344,"featureIndex":28,"threshold":-0.23189234733581544,"left":{"aggregate":[0.0,32.0]},"right":{"aggregate":[6.0,28.0]}},"right":{"aggregate":[18.0,15.0]}}}}}}},"right":{"weight":0.038214921951293948,"featureIndex":157,"threshold":-0.08155608177185059,"left":{"weight":0.07550537586212158,"featureIndex":180,"threshold":-1.586388111114502,"left":{"aggregate":[6.0,13.0]},"right":{"weight":0.09164983034133911,"featureIndex":323,"partition":[true,false,true,false,true,true,false,false,false,false,false,false,false,false,true,true,true,true,false,false,false,true,false,false,true,false,false,true],"left":{"aggregate":[63.0,0.0]},"right":{"weight":0.06263130903244019,"featureIndex":5,"threshold":-2.8346636295318605,"left":{"aggregate":[0.0,4.0]},"right":{"weight":0.07842439413070679,"featureIndex":51,"threshold":-1.0406150817871094,"left":{"aggregate":[29.0,0.0]},"right":{"weight":0.22168779373168946,"featureIndex":319,"partition":[false,true,true,false,true,false,true,true,true,false,true,false,false,true,false,false,true,false,false,false,false,true,false,false,false,false,true,false,false,false,false,false,true,false,false,false,false,false,false,false,false,false,false,false,false,false,false,false,false,false,false],"left":{"aggregate":[54.0,2.0]},"right":{"aggregate":[27.0,26.0]}}}}}},"right":{"weight":0.05331730842590332,"featureIndex":124,"threshold":1.1115450859069825,"left":{"weight":0.07155823707580567,"featureIndex":177,"threshold":1.341240644454956,"left":{"weight":0.06861728429794312,"featureIndex":325,"partition":[true,true,false,true,true,false,false,true],"left":{"aggregate":[6.0,19.0]},"right":{"weight":0.08903181552886963,"featureIndex":330,"partition":[true,false,true,false,false,false,false,false,true,false,true,false,false,true,false,true,true,false,false,false],"left":{"weight":0.12008148431777954,"featureIndex":31,"threshold":0.6133115291595459,"left":{"weight":0.1232907772064209,"featureIndex":254,"threshold":0.19245028495788575,"left":{"aggregate":[48.0,11.0]},"right":{"aggregate":[12.0,18.0]}},"right":{"aggregate":[30.0,0.0]}},"right":{"aggregate":[10.0,20.0]}}},"right":{"aggregate":[21.0,0.0]}},"right":{"aggregate":[13.0,30.0]}}}}