{"weight":0.0194244384765625,"featureIndex":321,"threshold":-0.6470329761505127,"left":{"weight":0.0327494740486145,"featureIndex":31,"threshold":-1.0644216537475587,"left":{"aggregate":[20.0,35.0]},"right":{"weight":0.11051225662231446,"featureIndex":304,"partition":[true,false,false,true,false,false,false,true,true,true,false,true,false,false,true,false,true,true,true,false,true,true,false,true,true,false,false,true,false,false,true,false,false,false],"left":{"weight":0.0840991735458374,"featureIndex":304,"partition":[false,true,false,true,true,true,true,true,true,true,true,true,true,false,true,false,false,false,false,true,false,false,true,false,false,true,true,false,false,false,false,true,true,false],"left":{"aggregate":[0.0,14.0]},"right":{"weight":0.2091403603553772,"featureIndex":298,"partition":[false,true,true,true,false,false,false,true,false,false,true,true,false,false,false,true,true,false,false,true,false,false,false,false,false,false,false,false,false,false,false,false,true,true,false,false,false,true,false,false,true,false,false,false,true,false,false,false,false],"left":{"weight":0.18297913670539857,"featureIndex":157,"threshold":-0.31360483169555666,"left":{"aggregate":[42.0,1.0]},"right":{"aggregate":[18.0,12.0]}},"right":{"weight":0.10625344514846802,"featureIndex":270,"threshold":1.2611398696899415,"left":{"weight":0.18563616275787354,"featureIndex":330,"partition":[true,false,true,true,true,true,true,false,false,true,true,true,true,false,true,true,true,false,true,false],"left":{"aggregate":[7.0,0.0]},"right":{"weight":0.1241455078125,"featureIndex":300,"partition":[false,false,true,false,false,false,false,false,false,false,false,false,true,true,true,false,true,false,false,true,true,true,true,false,true,true,true,true,true,false,false,false,false,false,false,false,false,false,false,false,false,false,false,false,false,false,false,false,false,true,false,false,false,false,false,false,false,false,false,false,false,false,false,false,false,false],"left":{"aggregate":[0.0,25.0]},"right":{"aggregate":[14.0,36.0]}}},"right":{"aggregate":[5.0,0.0]}}}},"right":{"weight":0.03745555877685547,"featureIndex":206,"threshold":-2.531126022338867,"left":{"aggregate":[0.0,2.0]},"right":{"weight":0.0967971682548523,"featureIndex":331,"threshold":0.09608578681945801,"left":{"weight":0.13635122776031495,"featureIndex":165,"threshold":-0.016407012939453126,"left":{"aggregate":[21.0,16.0]},"right":{"aggregate":[39.0,3.0]}},"right":{"weight":0.006381213665008545,"featureIndex":302,"partition":[false,true,true,false,true,true,true,false,false,false,true,false,false,false,false,false,false],"left":{"aggregate":[19.0,0.0]},"right":{"aggregate":[51.0,1.0]}}}}}},"right":{"weight":0.020016193389892579,"featureIndex":330,"partition":[false,true,true,false,false,true,true,false,true,true,false,true,false,false,false,false,true,false,false,false],"left":{"weight":0.03741347789764404,"featureIndex":34,"threshold":0.153411865234375,"left":{"weight":0.06335711479187012,"featureIndex":90,"threshold":1.707423448562622,"left":{"weight":0.06109142303466797,"featureIndex":135,"threshold":1.6638200283050538,"left":{"weight":0.08798223733901978,"featureIndex":329,"partition":[false,false,false,false,true,false,false,false,false,false,true,false,false,false,false,true,false,true,false,false],"left":{"weight":0.1477070450782776,"featureIndex":304,"partition":[true,true,false,true,false,false,true,false,true,true,false,true,true,false,false,false,true,false,false,false,false,false,false,false,true,true,false,false,false,false,false,false,false,false],"left":{"weight":0.21832674741744996,"featureIndex":327,"partition":[true,false,false,false,false,false,false,false,false,false,false,false,false,true,false,false,false,false,false,false,false,false,false,false,false,false,false,false,false,false,false,false,false,false,false,true,true,false,false,false,true,false,false,false,false,false,false,false,false,false,false,false,false,false,false,false,false,false,false,false],"left":{"weight":0.14435975253582,"featureIndex":300,"partition":[false,false,false,false,false,false,false,false,false,false,false,false,false,false,false,false,false,false,false,false,false,false,false,false,false,false,false,false,false,true,false,true,false,false,false,false,false,false,false,false,false,false,false,false,false,false,false,false,false,false,false,false,true,false,false,false,false,false,false,false,false,false,false,false,false,false],"left":{"weight":0.05943857133388519,"featureIndex":28,"threshold":-2.1232762336730959,"left":{"aggregate":[1.0,0.0]},"right":{"weight":0.03685781732201576,"featureIndex":44,"threshold":-1.0911715030670167,"left":{"aggregate":[1.0,7.0]},"right":{"aggregate":[0.0,94.0]}}},"right":{"aggregate":[4.0,1.0]}},"right":{"aggregate":[7.0,0.0]}},"right":{"weight":0.14487051963806153,"featureIndex":261,"threshold":-0.16060781478881837,"left":{"aggregate":[9.0,28.0]},"right":{"aggregate":[41.0,18.0]}}},"right":{"aggregate":[25.0,6.0]}},"right":{"aggregate":[11.0,0.0]}},"right":{"aggregate":[20.0,2.0]}},"right":{"weight":0.08052295446395874,"featureIndex":197,"threshold":0.3320486545562744,"left":{"weight":0.12336558103561402,"featureIndex":184,"threshold":-0.2873861789703369,"left":{"aggregate":[44.0,15.0]},"right":{"aggregate":[18.0,35.0]}},"right":{"aggregate":[53.0,8.0]}}},"right":{"weight":0.03591454029083252,"featureIndex":336,"threshold":-1.18389093875885,"left":{"aggregate":[32.0,16.0]},"right":{"weight":0.08249795436859131,"featureIndex":336,"threshold":-0.7468465566635132,"left":{"weight":0.10560239851474762,"featureIndex":320,"threshold":1.2553730010986329,"left":{"weight":0.04281144589185715,"featureIndex":327,"partition":[true,false,false,true,false,false,true,false,false,false,false,true,false,false,false,false,false,false,false,false,false,false,false,false,false,false,false,false,false,false,false,false,false,false,false,false,false,false,false,false,false,false,false,false,false,false,false,false,false,false,false,false,false,false,false,false,false,false,false,false],"left":{"aggregate":[2.0,23.0]},"right":{"aggregate":[0.0,57.0]}},"right":{"aggregate":[3.0,2.0]}},"right":{"weight":0.13433051109313966,"featureIndex":0,"partition":[false,false,false,false,false,true,false,false,false,false,false,true,false,false,true,true,false,false,false],"left":{"weight":0.21969175338745118,"featureIndex":319,"partition":[true,false,true,false,false,true,true,true,false,false,false,false,true,false,false,false,false,false,false,false,false,false,true,true,false,false,true,false,false,false,true,false,false,true,false,false,true,true,true,false,false,true,false,false,false,false,true,false,true,false,false],"left":{"weight":0.06468921899795532,"featureIndex":279,"threshold":-0.2818727493286133,"left":{"weight":0.13383173942565919,"featureIndex":322,"partition":[false,false,false,false,false,true,false,true,false,true,false,false,false,false,true,true,false,true,true,false,false,true,false,false,false,false,false],"left":{"aggregate":[4.0,10.0]},"right":{"aggregate":[0.0,68.0]}},"right":{"weight":0.07073909044265747,"featureIndex":270,"threshold":1.3362298011779786,"left":{"weight":0.08963203430175781,"featureIndex":189,"threshold":0.4726083278656006,"left":{"aggregate":[27.0,36.0]},"right":{"aggregate":[4.0,33.0]}},"right":{"aggregate":[0.0,17.0]}}},"right":{"weight":0.20695942640304566,"featureIndex":294,"threshold":-0.43551015853881838,"left":{"aggregate":[23.0,14.0]},"right":{"aggregate":[28.0,0.0]}}},"right":{"aggregate":[31.0,1.0]}}}}}}